henson_s3.py
Henson_S3-0.1.0.dist-info/DESCRIPTION.rst
Henson_S3-0.1.0.dist-info/METADATA
Henson_S3-0.1.0.dist-info/RECORD
Henson_S3-0.1.0.dist-info/WHEEL
Henson_S3-0.1.0.dist-info/metadata.json
Henson_S3-0.1.0.dist-info/top_level.txt
