Metadata-Version: 2.0
Name: Henson-S3
Version: 0.1.0
Summary: A library for easily using S3 in a Henson application.
Home-page: https://henson-s3.readthedocs.io
Author: Andy Dirnberger
Author-email: andy@dirnberger.me
License: MIT
Platform: UNKNOWN
Classifier: Development Status :: 4 - Beta
Classifier: Intended Audience :: Developers
Classifier: License :: OSI Approved :: MIT License
Classifier: Operating System :: OS Independent
Classifier: Programming Language :: Python
Classifier: Programming Language :: Python :: 3.5
Classifier: Programming Language :: Python :: 3.6
Classifier: Programming Language :: Python :: 3 :: Only
Classifier: Topic :: Software Development
Requires-Python: >=3.5
Requires-Dist: Henson
Requires-Dist: boto3
